openmetadata_managed_apis/__init__.py
openmetadata_managed_apis/plugin.py
openmetadata_managed_apis/api/__init__.py
openmetadata_managed_apis/api/apis_metadata.py
openmetadata_managed_apis/api/app.py
openmetadata_managed_apis/api/config.py
openmetadata_managed_apis/api/error_handlers.py
openmetadata_managed_apis/api/response.py
openmetadata_managed_apis/api/utils.py
openmetadata_managed_apis/api/routes/__init__.py
openmetadata_managed_apis/api/routes/csrf_token.py
openmetadata_managed_apis/api/routes/delete.py
openmetadata_managed_apis/api/routes/deploy.py
openmetadata_managed_apis/api/routes/disable.py
openmetadata_managed_apis/api/routes/enable.py
openmetadata_managed_apis/api/routes/health.py
openmetadata_managed_apis/api/routes/health_auth.py
openmetadata_managed_apis/api/routes/ip.py
openmetadata_managed_apis/api/routes/kill.py
openmetadata_managed_apis/api/routes/last_dag_logs.py
openmetadata_managed_apis/api/routes/run_automation.py
openmetadata_managed_apis/api/routes/status.py
openmetadata_managed_apis/api/routes/trigger.py
openmetadata_managed_apis/operations/__init__.py
openmetadata_managed_apis/operations/delete.py
openmetadata_managed_apis/operations/deploy.py
openmetadata_managed_apis/operations/health.py
openmetadata_managed_apis/operations/kill_all.py
openmetadata_managed_apis/operations/last_dag_logs.py
openmetadata_managed_apis/operations/state.py
openmetadata_managed_apis/operations/status.py
openmetadata_managed_apis/operations/trigger.py
openmetadata_managed_apis/resources/__init__.py
openmetadata_managed_apis/resources/dag_runner.j2
openmetadata_managed_apis/utils/__init__.py
openmetadata_managed_apis/utils/airflow_version.py
openmetadata_managed_apis/utils/logger.py
openmetadata_managed_apis/utils/parser.py
openmetadata_managed_apis/utils/security_compat.py
openmetadata_managed_apis/views/__init__.py
openmetadata_managed_apis/views/rest_api.py
openmetadata_managed_apis/views/templates/rest_api/index.html
openmetadata_managed_apis-1.11.7.1.dist-info/LICENSE
openmetadata_managed_apis-1.11.7.1.dist-info/METADATA
openmetadata_managed_apis-1.11.7.1.dist-info/WHEEL
openmetadata_managed_apis-1.11.7.1.dist-info/entry_points.txt
openmetadata_managed_apis-1.11.7.1.dist-info/top_level.txt
openmetadata_managed_apis-1.11.7.1.dist-info/RECORD
