Metadata-Version: 2.1
Name: openmetadata_managed_apis
Version: 1.11.7.1
Summary: Airflow REST APIs to create and manage DAGS
Author: OpenMetadata Committers
License: Apache License
Project-URL: Homepage, https://open-metadata.org/
Project-URL: Documentation, https://docs.open-metadata.org/
Project-URL: Source, https://github.com/open-metadata/OpenMetadata
Requires-Python: >=3.9
License-File: LICENSE
Requires-Dist: pendulum ~=3.0
Requires-Dist: apache-airflow >=2.2.2
Requires-Dist: apache-airflow-providers-fab >=1.0.0
Requires-Dist: Flask ==2.2.5
Requires-Dist: Flask-Admin ==1.6.0
Requires-Dist: packaging >=20.0
Provides-Extra: dev
Requires-Dist: black ==22.3.0 ; extra == 'dev'
Requires-Dist: pytest ; extra == 'dev'
Requires-Dist: pylint ; extra == 'dev'
Requires-Dist: pytest-cov ; extra == 'dev'
Requires-Dist: isort ; extra == 'dev'
Requires-Dist: pycln ; extra == 'dev'
